json_to_avro/__init__.py
json_to_avro/avro_schema/__init__.py
json_to_avro/avro_schema/avro_schema_candidate.py
json_to_avro/avro_schema/mergeable_avro_schema.py
json_to_avro/avro_schema/registered_avro_schema.py
json_to_avro/avroable_data.py
json_to_avro/json_to_avro.py
json_to_avro/schema_provider.py
json_to_avro-0.1.0a4.dist-info/LICENSE
json_to_avro-0.1.0a4.dist-info/METADATA
json_to_avro-0.1.0a4.dist-info/WHEEL
json_to_avro-0.1.0a4.dist-info/RECORD
