Metadata-Version: 2.1
Name: json-to-avro
Version: 0.1.0a4
Summary: Convert arbitrary JSON data to avro serialized data, registering transitively backwards compatible schemas with Kafka Schema Registry along the way.
License: MIT
Author: Brad Boggs
Author-email: bboggs@streambit.software
Requires-Python: >=3.10,<4.0
Classifier: License :: OSI Approved :: MIT License
Classifier: Programming Language :: Python :: 3
Classifier: Programming Language :: Python :: 3.10
Classifier: Programming Language :: Python :: 3.11
Requires-Dist: loguru (>=0.7.0,<0.8.0)
Requires-Dist: python-schema-registry-client[avro] (>=2.4.3,<3.0.0)
